generalize/__init__.py
generalize/dataset/__init__.py
generalize/dataset/assert_array_shape.py
generalize/dataset/load_dataset.py
generalize/dataset/order_dataset.py
generalize/dataset/parse_labels_to_use.py
generalize/dataset/subset_dataset.py
generalize/dataset/utils.py
generalize/evaluate/__init__.py
generalize/evaluate/confusion_matrices.py
generalize/evaluate/confusion_matrix.py
generalize/evaluate/evaluate.py
generalize/evaluate/evaluate_binary_classifier.py
generalize/evaluate/evaluate_multiclass_classifier.py
generalize/evaluate/evaluate_regression.py
generalize/evaluate/evaluate_repetitions.py
generalize/evaluate/evaluate_splits.py
generalize/evaluate/prepare_inputs.py
generalize/evaluate/probability_densities.py
generalize/evaluate/roc_curves.py
generalize/evaluate/summarize_scores.py
generalize/model/__init__.py
generalize/model/cross_validate/__init__.py
generalize/model/cross_validate/cross_validate.py
generalize/model/cross_validate/grid_search.py
generalize/model/cross_validate/kfolder.py
generalize/model/cross_validate/nested_cross_validation.py
generalize/model/cross_validate/sklearn_cross_validate.py
generalize/model/full_model.py
generalize/model/pipeline/__init__.py
generalize/model/pipeline/pipeline_designer.py
generalize/model/pipeline/pipelines.py
generalize/model/transformers/__init__.py
generalize/model/transformers/clip_extremes.py
generalize/model/transformers/correlated_feature_remover.py
generalize/model/transformers/dim_wrapper.py
generalize/model/transformers/flatten_dim.py
generalize/model/transformers/index_feature_selector.py
generalize/model/transformers/mean_during_test.py
generalize/model/transformers/pca_by_explained_variance.py
generalize/model/transformers/row_scaler.py
generalize/model/univariate/__init__.py
generalize/model/univariate/calculate_tree_importance.py
generalize/model/univariate/cross_validate_univariate_models.py
generalize/model/univariate/evaluate_univariate_models.py
generalize-0.3.0.dist-info/METADATA
generalize-0.3.0.dist-info/WHEEL
generalize-0.3.0.dist-info/RECORD
