Metadata-Version: 2.3
Name: generalize
Version: 0.3.0
Summary: Machine learning tools for running repeated nested leave-one-dataset-out validation and more.
Author: Ludvig
Author-email: <mail@ludvigolsen.dk>
Requires-Python: >=3.9,<4.0
Classifier: Programming Language :: Python :: 3
Classifier: Programming Language :: Python :: 3.9
Classifier: Programming Language :: Python :: 3.10
Classifier: Programming Language :: Python :: 3.11
Classifier: Programming Language :: Python :: 3.12
Classifier: Programming Language :: Python :: 3.13
Requires-Dist: joblib (==1.4.2)
Requires-Dist: nattrs (>=0.2.2,<0.3.0)
Requires-Dist: numpy (==1.26.4)
Requires-Dist: pandas (==1.5.3)
Requires-Dist: scikit-learn (==1.0.2)
Requires-Dist: scipy (>=1.7.3,<2.0.0)
Requires-Dist: statsmodels (==0.14.1)
Requires-Dist: utipy (>=1.0.4,<2.0.0)
Project-URL: Changelog, https://github.com/ludvigolsen/generalize/blob/main/CHANGELOG.md
Project-URL: Issues, https://github.com/ludvigolsen/generalize/issues
Project-URL: Repository, https://github.com/ludvigolsen/generalize
